{
  "bakedAnimDatas": {
    "Front": {
      "md5": "e2fb777cf619304353f94b490d5126ab",
      "skipZeroFrameUpdate": false,
      "bakedMPDatas": {
        "Default": {
          "0": {
            "bakedStepInterval": 1,
            "frameCount": 1,
            "trsData": [
              6.0,
              1.0,
              1.0,
              1.0,
              0.0,
              0.0,
              0.0,
              8.0,
              1.0,
              1.0,
              1.0,
              1.0,
              0.0,
              0.0,
              0.0,
              1.0,
              6.0,
              1.0,
              1.0,
              1.0,
              1.0,
              1.0,
              1.0
            ]
          },
          "1": {
            "bakedStepInterval": 1,
            "frameCount": 1,
            "trsData": [
              6.0,
              1.0,
              1.0,
              1.0,
              0.0,
              1.8,
              0.0,
              8.0,
              1.0,
              1.0,
              1.0,
              1.0,
              -0.0,
              -0.0,
              0.0,
              1.0,
              6.0,
              1.0,
              1.0,
              1.0,
              1.0,
              1.0,
              1.0
            ]
          },
          "2": {
            "bakedStepInterval": 1,
            "frameCount": 1,
            "trsData": [
              6.0,
              0.0,
              0.0,
              0.0,
              1.9925,
              2.0959,
              0.0,
              8.0,
              0.0,
              0.0,
              0.0,
              0.0,
              0.0,
              0.0,
              0.0,
              1.0,
              6.0,
              0.0,
              0.0,
              0.0,
              1.0,
              1.0,
              1.0
            ]
          },
          "3": {
            "bakedStepInterval": 1,
            "frameCount": 1,
            "trsData": [
              6.0,
              1.0,
              1.0,
              1.0,
              0.0,
              4.0,
              0.0,
              8.0,
              1.0,
              1.0,
              1.0,
              1.0,
              0.0,
              0.0,
              0.0,
              1.0,
              6.0,
              1.0,
              1.0,
              1.0,
              1.0,
              1.0,
              1.0
            ]
          },
          "5": {
            "bakedStepInterval": 1,
            "frameCount": 1,
            "trsData": [
              6.0,
              0.0,
              0.0,
              0.0,
              2.2149,
              2.1002,
              0.0,
              8.0,
              0.0,
              0.0,
              0.0,
              0.0,
              0.0,
              0.0,
              0.0,
              1.0,
              6.0,
              0.0,
              0.0,
              0.0,
              1.0,
              1.0,
              1.0
            ]
          }
        },
        "Start": {
          "0": {
            "bakedStepInterval": 1,
            "frameCount": 1,
            "trsData": [
              6.0,
              1.0,
              1.0,
              1.0,
              0.0,
              0.0,
              0.0,
              8.0,
              1.0,
              1.0,
              1.0,
              1.0,
              0.0,
              0.0,
              0.0,
              1.0,
              6.0,
              1.0,
              1.0,
              1.0,
              1.0,
              1.0,
              1.0
            ]
          },
          "1": {
            "bakedStepInterval": 1,
            "frameCount": 1,
            "trsData": [
              6.0,
              1.0,
              1.0,
              1.0,
              0.0,
              1.8,
              0.0,
              8.0,
              1.0,
              1.0,
              1.0,
              1.0,
              -0.0,
              -0.0,
              0.0,
              1.0,
              6.0,
              1.0,
              1.0,
              1.0,
              1.0,
              1.0,
              1.0
            ]
          },
          "2": {
            "bakedStepInterval": 1,
            "frameCount": 31,
            "trsData": [
              66.0,
              0.0,
              0.0,
              1.0,
              1.9925,
              1.9925,
              1.9925,
              1.9925,
              1.9925,
              1.9925,
              1.9925,
              1.9925,
              1.9925,
              1.9925,
              1.9925,
              1.9925,
              1.9925,
              1.9925,
              1.9925,
              1.9925,
              1.9925,
              1.9925,
              1.9925,
              1.9925,
              1.9925,
              1.9925,
              1.9925,
              1.9925,
              1.9925,
              1.9925,
              1.9925,
              1.9925,
              1.9925,
              1.9925,
              1.9925,
              2.5121,
              2.524625,
              2.557156,
              2.605537,
              2.6662,
              2.756483,
              2.847374,
              2.935385,
              3.015769,
              3.083734,
              3.13578,
              3.170657,
              3.188883,
              3.1946,
              3.164869,
              3.101745,
              3.017411,
              2.917897,
              2.806012,
              2.683131,
              2.551271,
              2.410403,
              2.259534,
              2.095903,
              2.0959,
              2.0959,
              2.0959,
              2.0959,
              2.0959,
              2.0959,
              2.0959,
              0.0,
              8.0,
              1.0,
              1.0,
              1.0,
              1.0,
              0.0,
              0.0,
              0.0,
              1.0,
              6.0,
              1.0,
              1.0,
              1.0,
              1.0,
              1.0,
              1.0
            ]
          },
          "3": {
            "bakedStepInterval": 1,
            "frameCount": 1,
            "trsData": [
              6.0,
              1.0,
              1.0,
              1.0,
              0.0,
              4.0,
              0.0,
              8.0,
              1.0,
              1.0,
              1.0,
              1.0,
              0.0,
              0.0,
              0.0,
              1.0,
              6.0,
              1.0,
              1.0,
              1.0,
              1.0,
              1.0,
              1.0
            ]
          },
          "5": {
            "bakedStepInterval": 1,
            "frameCount": 31,
            "trsData": [
              36.0,
              1.0,
              0.0,
              1.0,
              2.2149,
              2.5164,
              2.528925,
              2.561456,
              2.609837,
              2.6705,
              2.760783,
              2.851675,
              2.939685,
              3.020069,
              3.088034,
              3.14008,
              3.174957,
              3.193183,
              3.1989,
              3.169169,
              3.106045,
              3.021711,
              2.922197,
              2.810312,
              2.687431,
              2.555571,
              2.414704,
              2.263834,
              2.100204,
              2.1002,
              2.1002,
              2.1002,
              2.1002,
              2.1002,
              2.1002,
              2.1002,
              0.0,
              8.0,
              1.0,
              1.0,
              1.0,
              1.0,
              0.0,
              0.0,
              0.0,
              1.0,
              6.0,
              1.0,
              1.0,
              1.0,
              1.0,
              1.0,
              1.0
            ]
          }
        },
        "Die": {
          "0": {
            "bakedStepInterval": 1,
            "frameCount": 1,
            "trsData": [
              6.0,
              1.0,
              1.0,
              1.0,
              0.0,
              0.0,
              0.0,
              8.0,
              1.0,
              1.0,
              1.0,
              1.0,
              0.0,
              0.0,
              0.0,
              1.0,
              6.0,
              1.0,
              1.0,
              1.0,
              1.0,
              1.0,
              1.0
            ]
          },
          "1": {
            "bakedStepInterval": 1,
            "frameCount": 1,
            "trsData": [
              6.0,
              1.0,
              1.0,
              1.0,
              0.0,
              1.8,
              0.0,
              8.0,
              1.0,
              1.0,
              1.0,
              1.0,
              -0.0,
              -0.0,
              0.0,
              1.0,
              6.0,
              1.0,
              1.0,
              1.0,
              1.0,
              1.0,
              1.0
            ]
          },
          "2": {
            "bakedStepInterval": 1,
            "frameCount": 1,
            "trsData": [
              6.0,
              1.0,
              1.0,
              1.0,
              1.9925,
              2.0959,
              0.0,
              8.0,
              1.0,
              1.0,
              1.0,
              1.0,
              0.0,
              0.0,
              0.0,
              1.0,
              6.0,
              1.0,
              1.0,
              1.0,
              1.0,
              1.0,
              1.0
            ]
          },
          "3": {
            "bakedStepInterval": 1,
            "frameCount": 1,
            "trsData": [
              6.0,
              1.0,
              1.0,
              1.0,
              0.0,
              4.0,
              0.0,
              8.0,
              1.0,
              1.0,
              1.0,
              1.0,
              0.0,
              0.0,
              0.0,
              1.0,
              6.0,
              1.0,
              1.0,
              1.0,
              1.0,
              1.0,
              1.0
            ]
          },
          "5": {
            "bakedStepInterval": 1,
            "frameCount": 1,
            "trsData": [
              6.0,
              1.0,
              1.0,
              1.0,
              2.2149,
              2.1002,
              0.0,
              8.0,
              1.0,
              1.0,
              1.0,
              1.0,
              0.0,
              0.0,
              0.0,
              1.0,
              6.0,
              1.0,
              1.0,
              1.0,
              1.0,
              1.0,
              1.0
            ]
          }
        },
        "Idle": {
          "0": {
            "bakedStepInterval": 1,
            "frameCount": 1,
            "trsData": [
              6.0,
              1.0,
              1.0,
              1.0,
              0.0,
              0.0,
              0.0,
              8.0,
              1.0,
              1.0,
              1.0,
              1.0,
              0.0,
              0.0,
              0.0,
              1.0,
              6.0,
              1.0,
              1.0,
              1.0,
              1.0,
              1.0,
              1.0
            ]
          },
          "1": {
            "bakedStepInterval": 1,
            "frameCount": 1,
            "trsData": [
              6.0,
              1.0,
              1.0,
              1.0,
              0.0,
              1.8,
              0.0,
              8.0,
              1.0,
              1.0,
              1.0,
              1.0,
              -0.0,
              -0.0,
              0.0,
              1.0,
              6.0,
              1.0,
              1.0,
              1.0,
              1.0,
              1.0,
              1.0
            ]
          },
          "2": {
            "bakedStepInterval": 1,
            "frameCount": 1,
            "trsData": [
              6.0,
              1.0,
              1.0,
              1.0,
              1.9925,
              2.0959,
              0.0,
              8.0,
              1.0,
              1.0,
              1.0,
              1.0,
              0.0,
              0.0,
              0.0,
              1.0,
              6.0,
              1.0,
              1.0,
              1.0,
              1.0,
              1.0,
              1.0
            ]
          },
          "3": {
            "bakedStepInterval": 1,
            "frameCount": 1,
            "trsData": [
              6.0,
              1.0,
              1.0,
              1.0,
              0.0,
              4.0,
              0.0,
              8.0,
              1.0,
              1.0,
              1.0,
              1.0,
              0.0,
              0.0,
              0.0,
              1.0,
              6.0,
              1.0,
              1.0,
              1.0,
              1.0,
              1.0,
              1.0
            ]
          },
          "5": {
            "bakedStepInterval": 1,
            "frameCount": 1,
            "trsData": [
              6.0,
              1.0,
              1.0,
              1.0,
              2.2149,
              2.1002,
              0.0,
              8.0,
              1.0,
              1.0,
              1.0,
              1.0,
              0.0,
              0.0,
              0.0,
              1.0,
              6.0,
              1.0,
              1.0,
              1.0,
              1.0,
              1.0,
              1.0
            ]
          }
        },
        "Attack": {
          "0": {
            "bakedStepInterval": 1,
            "frameCount": 1,
            "trsData": [
              6.0,
              1.0,
              1.0,
              1.0,
              0.0,
              0.0,
              0.0,
              8.0,
              1.0,
              1.0,
              1.0,
              1.0,
              0.0,
              0.0,
              0.0,
              1.0,
              6.0,
              1.0,
              1.0,
              1.0,
              1.0,
              1.0,
              1.0
            ]
          },
          "1": {
            "bakedStepInterval": 1,
            "frameCount": 1,
            "trsData": [
              6.0,
              1.0,
              1.0,
              1.0,
              0.0,
              1.8,
              0.0,
              8.0,
              1.0,
              1.0,
              1.0,
              1.0,
              -0.0,
              -0.0,
              0.0,
              1.0,
              6.0,
              1.0,
              1.0,
              1.0,
              1.0,
              1.0,
              1.0
            ]
          },
          "2": {
            "bakedStepInterval": 1,
            "frameCount": 1,
            "trsData": [
              6.0,
              1.0,
              1.0,
              1.0,
              1.9925,
              2.0959,
              0.0,
              8.0,
              1.0,
              1.0,
              1.0,
              1.0,
              0.0,
              0.0,
              0.0,
              1.0,
              6.0,
              1.0,
              1.0,
              1.0,
              1.0,
              1.0,
              1.0
            ]
          },
          "3": {
            "bakedStepInterval": 1,
            "frameCount": 1,
            "trsData": [
              6.0,
              1.0,
              1.0,
              1.0,
              0.0,
              4.0,
              0.0,
              8.0,
              1.0,
              1.0,
              1.0,
              1.0,
              0.0,
              0.0,
              0.0,
              1.0,
              6.0,
              1.0,
              1.0,
              1.0,
              1.0,
              1.0,
              1.0
            ]
          },
          "5": {
            "bakedStepInterval": 1,
            "frameCount": 1,
            "trsData": [
              6.0,
              1.0,
              1.0,
              1.0,
              1.0201,
              1.7028,
              0.0,
              8.0,
              1.0,
              1.0,
              1.0,
              1.0,
              0.0,
              0.0,
              0.0,
              1.0,
              6.0,
              1.0,
              1.0,
              1.0,
              1.0,
              1.0,
              1.0
            ]
          }
        },
        "Combat": {
          "0": {
            "bakedStepInterval": 1,
            "frameCount": 1,
            "trsData": [
              6.0,
              1.0,
              1.0,
              1.0,
              0.0,
              0.0,
              0.0,
              8.0,
              1.0,
              1.0,
              1.0,
              1.0,
              0.0,
              0.0,
              0.0,
              1.0,
              6.0,
              1.0,
              1.0,
              1.0,
              1.0,
              1.0,
              1.0
            ]
          },
          "1": {
            "bakedStepInterval": 1,
            "frameCount": 1,
            "trsData": [
              6.0,
              1.0,
              1.0,
              1.0,
              0.0,
              1.8,
              0.0,
              8.0,
              1.0,
              1.0,
              1.0,
              1.0,
              -0.0,
              -0.0,
              0.0,
              1.0,
              6.0,
              1.0,
              1.0,
              1.0,
              1.0,
              1.0,
              1.0
            ]
          },
          "2": {
            "bakedStepInterval": 1,
            "frameCount": 1,
            "trsData": [
              6.0,
              1.0,
              1.0,
              1.0,
              1.9925,
              2.0959,
              0.0,
              8.0,
              1.0,
              1.0,
              1.0,
              1.0,
              0.0,
              0.0,
              0.0,
              1.0,
              6.0,
              1.0,
              1.0,
              1.0,
              1.0,
              1.0,
              1.0
            ]
          },
          "3": {
            "bakedStepInterval": 1,
            "frameCount": 1,
            "trsData": [
              6.0,
              1.0,
              1.0,
              1.0,
              0.0,
              4.0,
              0.0,
              8.0,
              1.0,
              1.0,
              1.0,
              1.0,
              0.0,
              0.0,
              0.0,
              1.0,
              6.0,
              1.0,
              1.0,
              1.0,
              1.0,
              1.0,
              1.0
            ]
          },
          "5": {
            "bakedStepInterval": 1,
            "frameCount": 1,
            "trsData": [
              6.0,
              1.0,
              1.0,
              1.0,
              2.2149,
              2.1002,
              0.0,
              8.0,
              1.0,
              1.0,
              1.0,
              1.0,
              0.0,
              0.0,
              0.0,
              1.0,
              6.0,
              1.0,
              1.0,
              1.0,
              1.0,
              1.0,
              1.0
            ]
          }
        },
        "Skill_2_Attack": {
          "0": {
            "bakedStepInterval": 1,
            "frameCount": 1,
            "trsData": [
              6.0,
              1.0,
              1.0,
              1.0,
              0.0,
              0.0,
              0.0,
              8.0,
              1.0,
              1.0,
              1.0,
              1.0,
              0.0,
              0.0,
              0.0,
              1.0,
              6.0,
              1.0,
              1.0,
              1.0,
              1.0,
              1.0,
              1.0
            ]
          },
          "1": {
            "bakedStepInterval": 1,
            "frameCount": 1,
            "trsData": [
              6.0,
              1.0,
              1.0,
              1.0,
              0.0,
              1.8,
              0.0,
              8.0,
              1.0,
              1.0,
              1.0,
              1.0,
              -0.0,
              -0.0,
              0.0,
              1.0,
              6.0,
              1.0,
              1.0,
              1.0,
              1.0,
              1.0,
              1.0
            ]
          },
          "2": {
            "bakedStepInterval": 1,
            "frameCount": 1,
            "trsData": [
              6.0,
              1.0,
              1.0,
              1.0,
              2.3445,
              1.9295,
              0.0,
              8.0,
              1.0,
              1.0,
              1.0,
              1.0,
              0.0,
              0.0,
              0.0,
              1.0,
              6.0,
              1.0,
              1.0,
              1.0,
              1.0,
              1.0,
              1.0
            ]
          },
          "3": {
            "bakedStepInterval": 1,
            "frameCount": 1,
            "trsData": [
              6.0,
              1.0,
              1.0,
              1.0,
              0.0,
              4.0,
              0.0,
              8.0,
              1.0,
              1.0,
              1.0,
              1.0,
              0.0,
              0.0,
              0.0,
              1.0,
              6.0,
              1.0,
              1.0,
              1.0,
              1.0,
              1.0,
              1.0
            ]
          },
          "5": {
            "bakedStepInterval": 1,
            "frameCount": 1,
            "trsData": [
              6.0,
              1.0,
              1.0,
              1.0,
              0.9345,
              1.6299,
              0.0,
              8.0,
              1.0,
              1.0,
              1.0,
              1.0,
              0.0,
              0.0,
              0.0,
              1.0,
              6.0,
              1.0,
              1.0,
              1.0,
              1.0,
              1.0,
              1.0
            ]
          }
        },
        "Skill_2_Begin": {
          "0": {
            "bakedStepInterval": 1,
            "frameCount": 1,
            "trsData": [
              6.0,
              1.0,
              1.0,
              1.0,
              0.0,
              0.0,
              0.0,
              8.0,
              1.0,
              1.0,
              1.0,
              1.0,
              0.0,
              0.0,
              0.0,
              1.0,
              6.0,
              1.0,
              1.0,
              1.0,
              1.0,
              1.0,
              1.0
            ]
          },
          "1": {
            "bakedStepInterval": 1,
            "frameCount": 1,
            "trsData": [
              6.0,
              1.0,
              1.0,
              1.0,
              0.0,
              1.8,
              0.0,
              8.0,
              1.0,
              1.0,
              1.0,
              1.0,
              -0.0,
              -0.0,
              0.0,
              1.0,
              6.0,
              1.0,
              1.0,
              1.0,
              1.0,
              1.0,
              1.0
            ]
          },
          "2": {
            "bakedStepInterval": 1,
            "frameCount": 1,
            "trsData": [
              6.0,
              1.0,
              1.0,
              1.0,
              1.9925,
              2.0959,
              0.0,
              8.0,
              1.0,
              1.0,
              1.0,
              1.0,
              0.0,
              0.0,
              0.0,
              1.0,
              6.0,
              1.0,
              1.0,
              1.0,
              1.0,
              1.0,
              1.0
            ]
          },
          "3": {
            "bakedStepInterval": 1,
            "frameCount": 1,
            "trsData": [
              6.0,
              1.0,
              1.0,
              1.0,
              0.0,
              4.0,
              0.0,
              8.0,
              1.0,
              1.0,
              1.0,
              1.0,
              0.0,
              0.0,
              0.0,
              1.0,
              6.0,
              1.0,
              1.0,
              1.0,
              1.0,
              1.0,
              1.0
            ]
          },
          "5": {
            "bakedStepInterval": 1,
            "frameCount": 1,
            "trsData": [
              6.0,
              1.0,
              1.0,
              1.0,
              2.2149,
              2.1002,
              0.0,
              8.0,
              1.0,
              1.0,
              1.0,
              1.0,
              0.0,
              0.0,
              0.0,
              1.0,
              6.0,
              1.0,
              1.0,
              1.0,
              1.0,
              1.0,
              1.0
            ]
          }
        },
        "Skill_2_Combat": {
          "0": {
            "bakedStepInterval": 1,
            "frameCount": 1,
            "trsData": [
              6.0,
              1.0,
              1.0,
              1.0,
              0.0,
              0.0,
              0.0,
              8.0,
              1.0,
              1.0,
              1.0,
              1.0,
              0.0,
              0.0,
              0.0,
              1.0,
              6.0,
              1.0,
              1.0,
              1.0,
              1.0,
              1.0,
              1.0
            ]
          },
          "1": {
            "bakedStepInterval": 1,
            "frameCount": 1,
            "trsData": [
              6.0,
              1.0,
              1.0,
              1.0,
              0.0,
              1.8,
              0.0,
              8.0,
              1.0,
              1.0,
              1.0,
              1.0,
              -0.0,
              -0.0,
              0.0,
              1.0,
              6.0,
              1.0,
              1.0,
              1.0,
              1.0,
              1.0,
              1.0
            ]
          },
          "2": {
            "bakedStepInterval": 1,
            "frameCount": 1,
            "trsData": [
              6.0,
              1.0,
              1.0,
              1.0,
              1.9925,
              2.0959,
              0.0,
              8.0,
              1.0,
              1.0,
              1.0,
              1.0,
              0.0,
              0.0,
              0.0,
              1.0,
              6.0,
              1.0,
              1.0,
              1.0,
              1.0,
              1.0,
              1.0
            ]
          },
          "3": {
            "bakedStepInterval": 1,
            "frameCount": 1,
            "trsData": [
              6.0,
              1.0,
              1.0,
              1.0,
              0.0,
              4.0,
              0.0,
              8.0,
              1.0,
              1.0,
              1.0,
              1.0,
              0.0,
              0.0,
              0.0,
              1.0,
              6.0,
              1.0,
              1.0,
              1.0,
              1.0,
              1.0,
              1.0
            ]
          },
          "5": {
            "bakedStepInterval": 1,
            "frameCount": 1,
            "trsData": [
              6.0,
              1.0,
              1.0,
              1.0,
              2.2149,
              2.1002,
              0.0,
              8.0,
              1.0,
              1.0,
              1.0,
              1.0,
              0.0,
              0.0,
              0.0,
              1.0,
              6.0,
              1.0,
              1.0,
              1.0,
              1.0,
              1.0,
              1.0
            ]
          }
        },
        "Skill_2_End": {
          "0": {
            "bakedStepInterval": 1,
            "frameCount": 1,
            "trsData": [
              6.0,
              1.0,
              1.0,
              1.0,
              0.0,
              0.0,
              0.0,
              8.0,
              1.0,
              1.0,
              1.0,
              1.0,
              0.0,
              0.0,
              0.0,
              1.0,
              6.0,
              1.0,
              1.0,
              1.0,
              1.0,
              1.0,
              1.0
            ]
          },
          "1": {
            "bakedStepInterval": 1,
            "frameCount": 1,
            "trsData": [
              6.0,
              1.0,
              1.0,
              1.0,
              0.0,
              1.8,
              0.0,
              8.0,
              1.0,
              1.0,
              1.0,
              1.0,
              -0.0,
              -0.0,
              0.0,
              1.0,
              6.0,
              1.0,
              1.0,
              1.0,
              1.0,
              1.0,
              1.0
            ]
          },
          "2": {
            "bakedStepInterval": 1,
            "frameCount": 1,
            "trsData": [
              6.0,
              1.0,
              1.0,
              1.0,
              1.9925,
              2.0959,
              0.0,
              8.0,
              1.0,
              1.0,
              1.0,
              1.0,
              0.0,
              0.0,
              0.0,
              1.0,
              6.0,
              1.0,
              1.0,
              1.0,
              1.0,
              1.0,
              1.0
            ]
          },
          "3": {
            "bakedStepInterval": 1,
            "frameCount": 1,
            "trsData": [
              6.0,
              1.0,
              1.0,
              1.0,
              0.0,
              4.0,
              0.0,
              8.0,
              1.0,
              1.0,
              1.0,
              1.0,
              0.0,
              0.0,
              0.0,
              1.0,
              6.0,
              1.0,
              1.0,
              1.0,
              1.0,
              1.0,
              1.0
            ]
          },
          "5": {
            "bakedStepInterval": 1,
            "frameCount": 1,
            "trsData": [
              6.0,
              1.0,
              1.0,
              1.0,
              2.2149,
              2.1002,
              0.0,
              8.0,
              1.0,
              1.0,
              1.0,
              1.0,
              0.0,
              0.0,
              0.0,
              1.0,
              6.0,
              1.0,
              1.0,
              1.0,
              1.0,
              1.0,
              1.0
            ]
          }
        },
        "Skill_2_Idle": {
          "0": {
            "bakedStepInterval": 1,
            "frameCount": 1,
            "trsData": [
              6.0,
              1.0,
              1.0,
              1.0,
              0.0,
              0.0,
              0.0,
              8.0,
              1.0,
              1.0,
              1.0,
              1.0,
              0.0,
              0.0,
              0.0,
              1.0,
              6.0,
              1.0,
              1.0,
              1.0,
              1.0,
              1.0,
              1.0
            ]
          },
          "1": {
            "bakedStepInterval": 1,
            "frameCount": 1,
            "trsData": [
              6.0,
              1.0,
              1.0,
              1.0,
              0.0,
              1.8,
              0.0,
              8.0,
              1.0,
              1.0,
              1.0,
              1.0,
              -0.0,
              -0.0,
              0.0,
              1.0,
              6.0,
              1.0,
              1.0,
              1.0,
              1.0,
              1.0,
              1.0
            ]
          },
          "2": {
            "bakedStepInterval": 1,
            "frameCount": 1,
            "trsData": [
              6.0,
              1.0,
              1.0,
              1.0,
              1.9925,
              2.0959,
              0.0,
              8.0,
              1.0,
              1.0,
              1.0,
              1.0,
              0.0,
              0.0,
              0.0,
              1.0,
              6.0,
              1.0,
              1.0,
              1.0,
              1.0,
              1.0,
              1.0
            ]
          },
          "3": {
            "bakedStepInterval": 1,
            "frameCount": 1,
            "trsData": [
              6.0,
              1.0,
              1.0,
              1.0,
              0.0,
              4.0,
              0.0,
              8.0,
              1.0,
              1.0,
              1.0,
              1.0,
              0.0,
              0.0,
              0.0,
              1.0,
              6.0,
              1.0,
              1.0,
              1.0,
              1.0,
              1.0,
              1.0
            ]
          },
          "5": {
            "bakedStepInterval": 1,
            "frameCount": 1,
            "trsData": [
              6.0,
              1.0,
              1.0,
              1.0,
              2.2149,
              2.1002,
              0.0,
              8.0,
              1.0,
              1.0,
              1.0,
              1.0,
              0.0,
              0.0,
              0.0,
              1.0,
              6.0,
              1.0,
              1.0,
              1.0,
              1.0,
              1.0,
              1.0
            ]
          }
        }
      },
      "bakedEvents": {
        "Start": {
          "eventTime": [
            0.533333
          ],
          "events": [
            "OnStart"
          ]
        },
        "Attack": {
          "eventTime": [
            0.4
          ],
          "events": [
            "OnAttack"
          ]
        },
        "Combat": {
          "eventTime": [
            0.4
          ],
          "events": [
            "OnAttack"
          ]
        },
        "Skill_2_Attack": {
          "eventTime": [
            0.333333
          ],
          "events": [
            "OnAttack"
          ]
        },
        "Skill_2_Combat": {
          "eventTime": [
            0.333333
          ],
          "events": [
            "OnAttack"
          ]
        }
      }
    },
    "Back": {
      "md5": "5e5e79d6427c16fdd027a860eb673869",
      "skipZeroFrameUpdate": false,
      "bakedMPDatas": {
        "Default": {
          "0": {
            "bakedStepInterval": 1,
            "frameCount": 1,
            "trsData": [
              6.0,
              1.0,
              1.0,
              1.0,
              0.0,
              0.0,
              0.0,
              8.0,
              1.0,
              1.0,
              1.0,
              1.0,
              0.0,
              0.0,
              0.0,
              1.0,
              6.0,
              1.0,
              1.0,
              1.0,
              1.0,
              1.0,
              1.0
            ]
          },
          "1": {
            "bakedStepInterval": 1,
            "frameCount": 1,
            "trsData": [
              6.0,
              1.0,
              1.0,
              1.0,
              0.0,
              1.8,
              0.0,
              8.0,
              1.0,
              1.0,
              1.0,
              1.0,
              -0.0,
              -0.0,
              0.0,
              1.0,
              6.0,
              1.0,
              1.0,
              1.0,
              1.0,
              1.0,
              1.0
            ]
          },
          "2": {
            "bakedStepInterval": 1,
            "frameCount": 1,
            "trsData": [
              6.0,
              0.0,
              0.0,
              0.0,
              1.9925,
              2.0959,
              0.0,
              8.0,
              0.0,
              0.0,
              0.0,
              0.0,
              0.0,
              0.0,
              0.0,
              1.0,
              6.0,
              0.0,
              0.0,
              0.0,
              1.0,
              1.0,
              1.0
            ]
          },
          "3": {
            "bakedStepInterval": 1,
            "frameCount": 1,
            "trsData": [
              6.0,
              1.0,
              1.0,
              1.0,
              0.0,
              4.0,
              0.0,
              8.0,
              1.0,
              1.0,
              1.0,
              1.0,
              0.0,
              0.0,
              0.0,
              1.0,
              6.0,
              1.0,
              1.0,
              1.0,
              1.0,
              1.0,
              1.0
            ]
          },
          "5": {
            "bakedStepInterval": 1,
            "frameCount": 1,
            "trsData": [
              6.0,
              0.0,
              0.0,
              0.0,
              2.2149,
              2.1002,
              0.0,
              8.0,
              0.0,
              0.0,
              0.0,
              0.0,
              0.0,
              0.0,
              0.0,
              1.0,
              6.0,
              0.0,
              0.0,
              0.0,
              1.0,
              1.0,
              1.0
            ]
          }
        },
        "Start": {
          "0": {
            "bakedStepInterval": 1,
            "frameCount": 1,
            "trsData": [
              6.0,
              1.0,
              1.0,
              1.0,
              0.0,
              0.0,
              0.0,
              8.0,
              1.0,
              1.0,
              1.0,
              1.0,
              0.0,
              0.0,
              0.0,
              1.0,
              6.0,
              1.0,
              1.0,
              1.0,
              1.0,
              1.0,
              1.0
            ]
          },
          "1": {
            "bakedStepInterval": 1,
            "frameCount": 1,
            "trsData": [
              6.0,
              1.0,
              1.0,
              1.0,
              0.0,
              1.8,
              0.0,
              8.0,
              1.0,
              1.0,
              1.0,
              1.0,
              -0.0,
              -0.0,
              0.0,
              1.0,
              6.0,
              1.0,
              1.0,
              1.0,
              1.0,
              1.0,
              1.0
            ]
          },
          "2": {
            "bakedStepInterval": 1,
            "frameCount": 31,
            "trsData": [
              66.0,
              0.0,
              0.0,
              1.0,
              1.9925,
              1.9925,
              1.9925,
              1.9925,
              1.9925,
              1.9925,
              1.9925,
              1.9925,
              1.9925,
              1.9925,
              1.9925,
              1.9925,
              1.9925,
              1.9925,
              1.9925,
              1.9925,
              1.9925,
              1.9925,
              1.9925,
              1.9925,
              1.9925,
              1.9925,
              1.9925,
              1.9925,
              1.9925,
              1.9925,
              1.9925,
              1.9925,
              1.9925,
              1.9925,
              1.9925,
              2.5121,
              2.524625,
              2.557156,
              2.605537,
              2.6662,
              2.756483,
              2.847374,
              2.935385,
              3.015769,
              3.083734,
              3.13578,
              3.170657,
              3.188883,
              3.1946,
              3.164869,
              3.101745,
              3.017411,
              2.917897,
              2.806012,
              2.683131,
              2.551271,
              2.410403,
              2.259534,
              2.095903,
              2.0959,
              2.0959,
              2.0959,
              2.0959,
              2.0959,
              2.0959,
              2.0959,
              0.0,
              8.0,
              1.0,
              1.0,
              1.0,
              1.0,
              0.0,
              0.0,
              0.0,
              1.0,
              6.0,
              1.0,
              1.0,
              1.0,
              1.0,
              1.0,
              1.0
            ]
          },
          "3": {
            "bakedStepInterval": 1,
            "frameCount": 1,
            "trsData": [
              6.0,
              1.0,
              1.0,
              1.0,
              0.0,
              4.0,
              0.0,
              8.0,
              1.0,
              1.0,
              1.0,
              1.0,
              0.0,
              0.0,
              0.0,
              1.0,
              6.0,
              1.0,
              1.0,
              1.0,
              1.0,
              1.0,
              1.0
            ]
          },
          "5": {
            "bakedStepInterval": 1,
            "frameCount": 31,
            "trsData": [
              36.0,
              1.0,
              0.0,
              1.0,
              2.2149,
              2.5164,
              2.528925,
              2.561456,
              2.609837,
              2.6705,
              2.760783,
              2.851675,
              2.939685,
              3.020069,
              3.088034,
              3.14008,
              3.174957,
              3.193183,
              3.1989,
              3.169169,
              3.106045,
              3.021711,
              2.922197,
              2.810312,
              2.687431,
              2.555571,
              2.414704,
              2.263834,
              2.100204,
              2.1002,
              2.1002,
              2.1002,
              2.1002,
              2.1002,
              2.1002,
              2.1002,
              0.0,
              8.0,
              1.0,
              1.0,
              1.0,
              1.0,
              0.0,
              0.0,
              0.0,
              1.0,
              6.0,
              1.0,
              1.0,
              1.0,
              1.0,
              1.0,
              1.0
            ]
          }
        },
        "Idle": {
          "0": {
            "bakedStepInterval": 1,
            "frameCount": 1,
            "trsData": [
              6.0,
              1.0,
              1.0,
              1.0,
              0.0,
              0.0,
              0.0,
              8.0,
              1.0,
              1.0,
              1.0,
              1.0,
              0.0,
              0.0,
              0.0,
              1.0,
              6.0,
              1.0,
              1.0,
              1.0,
              1.0,
              1.0,
              1.0
            ]
          },
          "1": {
            "bakedStepInterval": 1,
            "frameCount": 1,
            "trsData": [
              6.0,
              1.0,
              1.0,
              1.0,
              0.0,
              1.8,
              0.0,
              8.0,
              1.0,
              1.0,
              1.0,
              1.0,
              -0.0,
              -0.0,
              0.0,
              1.0,
              6.0,
              1.0,
              1.0,
              1.0,
              1.0,
              1.0,
              1.0
            ]
          },
          "2": {
            "bakedStepInterval": 1,
            "frameCount": 1,
            "trsData": [
              6.0,
              1.0,
              1.0,
              1.0,
              1.9925,
              2.0959,
              0.0,
              8.0,
              1.0,
              1.0,
              1.0,
              1.0,
              0.0,
              0.0,
              0.0,
              1.0,
              6.0,
              1.0,
              1.0,
              1.0,
              1.0,
              1.0,
              1.0
            ]
          },
          "3": {
            "bakedStepInterval": 1,
            "frameCount": 1,
            "trsData": [
              6.0,
              1.0,
              1.0,
              1.0,
              0.0,
              4.0,
              0.0,
              8.0,
              1.0,
              1.0,
              1.0,
              1.0,
              0.0,
              0.0,
              0.0,
              1.0,
              6.0,
              1.0,
              1.0,
              1.0,
              1.0,
              1.0,
              1.0
            ]
          },
          "5": {
            "bakedStepInterval": 1,
            "frameCount": 1,
            "trsData": [
              6.0,
              1.0,
              1.0,
              1.0,
              2.2149,
              2.1002,
              0.0,
              8.0,
              1.0,
              1.0,
              1.0,
              1.0,
              0.0,
              0.0,
              0.0,
              1.0,
              6.0,
              1.0,
              1.0,
              1.0,
              1.0,
              1.0,
              1.0
            ]
          }
        },
        "Attack": {
          "0": {
            "bakedStepInterval": 1,
            "frameCount": 1,
            "trsData": [
              6.0,
              1.0,
              1.0,
              1.0,
              0.0,
              0.0,
              0.0,
              8.0,
              1.0,
              1.0,
              1.0,
              1.0,
              0.0,
              0.0,
              0.0,
              1.0,
              6.0,
              1.0,
              1.0,
              1.0,
              1.0,
              1.0,
              1.0
            ]
          },
          "1": {
            "bakedStepInterval": 1,
            "frameCount": 1,
            "trsData": [
              6.0,
              1.0,
              1.0,
              1.0,
              0.0,
              1.8,
              0.0,
              8.0,
              1.0,
              1.0,
              1.0,
              1.0,
              -0.0,
              -0.0,
              0.0,
              1.0,
              6.0,
              1.0,
              1.0,
              1.0,
              1.0,
              1.0,
              1.0
            ]
          },
          "2": {
            "bakedStepInterval": 1,
            "frameCount": 1,
            "trsData": [
              6.0,
              1.0,
              1.0,
              1.0,
              1.9925,
              2.0959,
              0.0,
              8.0,
              1.0,
              1.0,
              1.0,
              1.0,
              0.0,
              0.0,
              0.0,
              1.0,
              6.0,
              1.0,
              1.0,
              1.0,
              1.0,
              1.0,
              1.0
            ]
          },
          "3": {
            "bakedStepInterval": 1,
            "frameCount": 1,
            "trsData": [
              6.0,
              1.0,
              1.0,
              1.0,
              0.0,
              4.0,
              0.0,
              8.0,
              1.0,
              1.0,
              1.0,
              1.0,
              0.0,
              0.0,
              0.0,
              1.0,
              6.0,
              1.0,
              1.0,
              1.0,
              1.0,
              1.0,
              1.0
            ]
          },
          "5": {
            "bakedStepInterval": 1,
            "frameCount": 1,
            "trsData": [
              6.0,
              1.0,
              1.0,
              1.0,
              0.9609,
              2.5825,
              0.0,
              8.0,
              1.0,
              1.0,
              1.0,
              1.0,
              0.0,
              0.0,
              0.0,
              1.0,
              6.0,
              1.0,
              1.0,
              1.0,
              1.0,
              1.0,
              1.0
            ]
          }
        },
        "Combat": {
          "0": {
            "bakedStepInterval": 1,
            "frameCount": 1,
            "trsData": [
              6.0,
              1.0,
              1.0,
              1.0,
              0.0,
              0.0,
              0.0,
              8.0,
              1.0,
              1.0,
              1.0,
              1.0,
              0.0,
              0.0,
              0.0,
              1.0,
              6.0,
              1.0,
              1.0,
              1.0,
              1.0,
              1.0,
              1.0
            ]
          },
          "1": {
            "bakedStepInterval": 1,
            "frameCount": 1,
            "trsData": [
              6.0,
              1.0,
              1.0,
              1.0,
              0.0,
              1.8,
              0.0,
              8.0,
              1.0,
              1.0,
              1.0,
              1.0,
              -0.0,
              -0.0,
              0.0,
              1.0,
              6.0,
              1.0,
              1.0,
              1.0,
              1.0,
              1.0,
              1.0
            ]
          },
          "2": {
            "bakedStepInterval": 1,
            "frameCount": 1,
            "trsData": [
              6.0,
              1.0,
              1.0,
              1.0,
              1.9925,
              2.0959,
              0.0,
              8.0,
              1.0,
              1.0,
              1.0,
              1.0,
              0.0,
              0.0,
              0.0,
              1.0,
              6.0,
              1.0,
              1.0,
              1.0,
              1.0,
              1.0,
              1.0
            ]
          },
          "3": {
            "bakedStepInterval": 1,
            "frameCount": 1,
            "trsData": [
              6.0,
              1.0,
              1.0,
              1.0,
              0.0,
              4.0,
              0.0,
              8.0,
              1.0,
              1.0,
              1.0,
              1.0,
              0.0,
              0.0,
              0.0,
              1.0,
              6.0,
              1.0,
              1.0,
              1.0,
              1.0,
              1.0,
              1.0
            ]
          },
          "5": {
            "bakedStepInterval": 1,
            "frameCount": 1,
            "trsData": [
              6.0,
              1.0,
              1.0,
              1.0,
              2.2149,
              2.1002,
              0.0,
              8.0,
              1.0,
              1.0,
              1.0,
              1.0,
              0.0,
              0.0,
              0.0,
              1.0,
              6.0,
              1.0,
              1.0,
              1.0,
              1.0,
              1.0,
              1.0
            ]
          }
        },
        "Skill_2_Attack": {
          "0": {
            "bakedStepInterval": 1,
            "frameCount": 1,
            "trsData": [
              6.0,
              1.0,
              1.0,
              1.0,
              0.0,
              0.0,
              0.0,
              8.0,
              1.0,
              1.0,
              1.0,
              1.0,
              0.0,
              0.0,
              0.0,
              1.0,
              6.0,
              1.0,
              1.0,
              1.0,
              1.0,
              1.0,
              1.0
            ]
          },
          "1": {
            "bakedStepInterval": 1,
            "frameCount": 1,
            "trsData": [
              6.0,
              1.0,
              1.0,
              1.0,
              0.0,
              1.8,
              0.0,
              8.0,
              1.0,
              1.0,
              1.0,
              1.0,
              -0.0,
              -0.0,
              0.0,
              1.0,
              6.0,
              1.0,
              1.0,
              1.0,
              1.0,
              1.0,
              1.0
            ]
          },
          "2": {
            "bakedStepInterval": 1,
            "frameCount": 1,
            "trsData": [
              6.0,
              1.0,
              1.0,
              1.0,
              2.4098,
              2.0335,
              0.0,
              8.0,
              1.0,
              1.0,
              1.0,
              1.0,
              0.0,
              0.0,
              0.0,
              1.0,
              6.0,
              1.0,
              1.0,
              1.0,
              1.0,
              1.0,
              1.0
            ]
          },
          "3": {
            "bakedStepInterval": 1,
            "frameCount": 1,
            "trsData": [
              6.0,
              1.0,
              1.0,
              1.0,
              0.0,
              4.0,
              0.0,
              8.0,
              1.0,
              1.0,
              1.0,
              1.0,
              0.0,
              0.0,
              0.0,
              1.0,
              6.0,
              1.0,
              1.0,
              1.0,
              1.0,
              1.0,
              1.0
            ]
          },
          "5": {
            "bakedStepInterval": 1,
            "frameCount": 1,
            "trsData": [
              6.0,
              1.0,
              1.0,
              1.0,
              0.951,
              2.6636,
              0.0,
              8.0,
              1.0,
              1.0,
              1.0,
              1.0,
              0.0,
              0.0,
              0.0,
              1.0,
              6.0,
              1.0,
              1.0,
              1.0,
              1.0,
              1.0,
              1.0
            ]
          }
        },
        "Skill_2_Begin": {
          "0": {
            "bakedStepInterval": 1,
            "frameCount": 1,
            "trsData": [
              6.0,
              1.0,
              1.0,
              1.0,
              0.0,
              0.0,
              0.0,
              8.0,
              1.0,
              1.0,
              1.0,
              1.0,
              0.0,
              0.0,
              0.0,
              1.0,
              6.0,
              1.0,
              1.0,
              1.0,
              1.0,
              1.0,
              1.0
            ]
          },
          "1": {
            "bakedStepInterval": 1,
            "frameCount": 1,
            "trsData": [
              6.0,
              1.0,
              1.0,
              1.0,
              0.0,
              1.8,
              0.0,
              8.0,
              1.0,
              1.0,
              1.0,
              1.0,
              -0.0,
              -0.0,
              0.0,
              1.0,
              6.0,
              1.0,
              1.0,
              1.0,
              1.0,
              1.0,
              1.0
            ]
          },
          "2": {
            "bakedStepInterval": 1,
            "frameCount": 1,
            "trsData": [
              6.0,
              1.0,
              1.0,
              1.0,
              1.9925,
              2.0959,
              0.0,
              8.0,
              1.0,
              1.0,
              1.0,
              1.0,
              0.0,
              0.0,
              0.0,
              1.0,
              6.0,
              1.0,
              1.0,
              1.0,
              1.0,
              1.0,
              1.0
            ]
          },
          "3": {
            "bakedStepInterval": 1,
            "frameCount": 1,
            "trsData": [
              6.0,
              1.0,
              1.0,
              1.0,
              0.0,
              4.0,
              0.0,
              8.0,
              1.0,
              1.0,
              1.0,
              1.0,
              0.0,
              0.0,
              0.0,
              1.0,
              6.0,
              1.0,
              1.0,
              1.0,
              1.0,
              1.0,
              1.0
            ]
          },
          "5": {
            "bakedStepInterval": 1,
            "frameCount": 1,
            "trsData": [
              6.0,
              1.0,
              1.0,
              1.0,
              2.2149,
              2.1002,
              0.0,
              8.0,
              1.0,
              1.0,
              1.0,
              1.0,
              0.0,
              0.0,
              0.0,
              1.0,
              6.0,
              1.0,
              1.0,
              1.0,
              1.0,
              1.0,
              1.0
            ]
          }
        },
        "Skill_2_Combat": {
          "0": {
            "bakedStepInterval": 1,
            "frameCount": 1,
            "trsData": [
              6.0,
              1.0,
              1.0,
              1.0,
              0.0,
              0.0,
              0.0,
              8.0,
              1.0,
              1.0,
              1.0,
              1.0,
              0.0,
              0.0,
              0.0,
              1.0,
              6.0,
              1.0,
              1.0,
              1.0,
              1.0,
              1.0,
              1.0
            ]
          },
          "1": {
            "bakedStepInterval": 1,
            "frameCount": 1,
            "trsData": [
              6.0,
              1.0,
              1.0,
              1.0,
              0.0,
              1.8,
              0.0,
              8.0,
              1.0,
              1.0,
              1.0,
              1.0,
              -0.0,
              -0.0,
              0.0,
              1.0,
              6.0,
              1.0,
              1.0,
              1.0,
              1.0,
              1.0,
              1.0
            ]
          },
          "2": {
            "bakedStepInterval": 1,
            "frameCount": 1,
            "trsData": [
              6.0,
              1.0,
              1.0,
              1.0,
              1.9925,
              2.0959,
              0.0,
              8.0,
              1.0,
              1.0,
              1.0,
              1.0,
              0.0,
              0.0,
              0.0,
              1.0,
              6.0,
              1.0,
              1.0,
              1.0,
              1.0,
              1.0,
              1.0
            ]
          },
          "3": {
            "bakedStepInterval": 1,
            "frameCount": 1,
            "trsData": [
              6.0,
              1.0,
              1.0,
              1.0,
              0.0,
              4.0,
              0.0,
              8.0,
              1.0,
              1.0,
              1.0,
              1.0,
              0.0,
              0.0,
              0.0,
              1.0,
              6.0,
              1.0,
              1.0,
              1.0,
              1.0,
              1.0,
              1.0
            ]
          },
          "5": {
            "bakedStepInterval": 1,
            "frameCount": 1,
            "trsData": [
              6.0,
              1.0,
              1.0,
              1.0,
              2.2149,
              2.1002,
              0.0,
              8.0,
              1.0,
              1.0,
              1.0,
              1.0,
              0.0,
              0.0,
              0.0,
              1.0,
              6.0,
              1.0,
              1.0,
              1.0,
              1.0,
              1.0,
              1.0
            ]
          }
        },
        "Skill_2_End": {
          "0": {
            "bakedStepInterval": 1,
            "frameCount": 1,
            "trsData": [
              6.0,
              1.0,
              1.0,
              1.0,
              0.0,
              0.0,
              0.0,
              8.0,
              1.0,
              1.0,
              1.0,
              1.0,
              0.0,
              0.0,
              0.0,
              1.0,
              6.0,
              1.0,
              1.0,
              1.0,
              1.0,
              1.0,
              1.0
            ]
          },
          "1": {
            "bakedStepInterval": 1,
            "frameCount": 1,
            "trsData": [
              6.0,
              1.0,
              1.0,
              1.0,
              0.0,
              1.8,
              0.0,
              8.0,
              1.0,
              1.0,
              1.0,
              1.0,
              -0.0,
              -0.0,
              0.0,
              1.0,
              6.0,
              1.0,
              1.0,
              1.0,
              1.0,
              1.0,
              1.0
            ]
          },
          "2": {
            "bakedStepInterval": 1,
            "frameCount": 1,
            "trsData": [
              6.0,
              1.0,
              1.0,
              1.0,
              1.9925,
              2.0959,
              0.0,
              8.0,
              1.0,
              1.0,
              1.0,
              1.0,
              0.0,
              0.0,
              0.0,
              1.0,
              6.0,
              1.0,
              1.0,
              1.0,
              1.0,
              1.0,
              1.0
            ]
          },
          "3": {
            "bakedStepInterval": 1,
            "frameCount": 1,
            "trsData": [
              6.0,
              1.0,
              1.0,
              1.0,
              0.0,
              4.0,
              0.0,
              8.0,
              1.0,
              1.0,
              1.0,
              1.0,
              0.0,
              0.0,
              0.0,
              1.0,
              6.0,
              1.0,
              1.0,
              1.0,
              1.0,
              1.0,
              1.0
            ]
          },
          "5": {
            "bakedStepInterval": 1,
            "frameCount": 1,
            "trsData": [
              6.0,
              1.0,
              1.0,
              1.0,
              2.2149,
              2.1002,
              0.0,
              8.0,
              1.0,
              1.0,
              1.0,
              1.0,
              0.0,
              0.0,
              0.0,
              1.0,
              6.0,
              1.0,
              1.0,
              1.0,
              1.0,
              1.0,
              1.0
            ]
          }
        },
        "Skill_2_Idle": {
          "0": {
            "bakedStepInterval": 1,
            "frameCount": 1,
            "trsData": [
              6.0,
              1.0,
              1.0,
              1.0,
              0.0,
              0.0,
              0.0,
              8.0,
              1.0,
              1.0,
              1.0,
              1.0,
              0.0,
              0.0,
              0.0,
              1.0,
              6.0,
              1.0,
              1.0,
              1.0,
              1.0,
              1.0,
              1.0
            ]
          },
          "1": {
            "bakedStepInterval": 1,
            "frameCount": 1,
            "trsData": [
              6.0,
              1.0,
              1.0,
              1.0,
              0.0,
              1.8,
              0.0,
              8.0,
              1.0,
              1.0,
              1.0,
              1.0,
              -0.0,
              -0.0,
              0.0,
              1.0,
              6.0,
              1.0,
              1.0,
              1.0,
              1.0,
              1.0,
              1.0
            ]
          },
          "2": {
            "bakedStepInterval": 1,
            "frameCount": 1,
            "trsData": [
              6.0,
              1.0,
              1.0,
              1.0,
              1.9925,
              2.0959,
              0.0,
              8.0,
              1.0,
              1.0,
              1.0,
              1.0,
              0.0,
              0.0,
              0.0,
              1.0,
              6.0,
              1.0,
              1.0,
              1.0,
              1.0,
              1.0,
              1.0
            ]
          },
          "3": {
            "bakedStepInterval": 1,
            "frameCount": 1,
            "trsData": [
              6.0,
              1.0,
              1.0,
              1.0,
              0.0,
              4.0,
              0.0,
              8.0,
              1.0,
              1.0,
              1.0,
              1.0,
              0.0,
              0.0,
              0.0,
              1.0,
              6.0,
              1.0,
              1.0,
              1.0,
              1.0,
              1.0,
              1.0
            ]
          },
          "5": {
            "bakedStepInterval": 1,
            "frameCount": 1,
            "trsData": [
              6.0,
              1.0,
              1.0,
              1.0,
              2.2149,
              2.1002,
              0.0,
              8.0,
              1.0,
              1.0,
              1.0,
              1.0,
              0.0,
              0.0,
              0.0,
              1.0,
              6.0,
              1.0,
              1.0,
              1.0,
              1.0,
              1.0,
              1.0
            ]
          }
        }
      },
      "bakedEvents": {
        "Start": {
          "eventTime": [
            0.533333
          ],
          "events": [
            "OnStart"
          ]
        },
        "Attack": {
          "eventTime": [
            0.4
          ],
          "events": [
            "OnAttack"
          ]
        },
        "Combat": {
          "eventTime": [
            0.4
          ],
          "events": [
            "OnAttack"
          ]
        },
        "Skill_2_Attack": {
          "eventTime": [
            0.333333
          ],
          "events": [
            "OnAttack"
          ]
        },
        "Skill_2_Combat": {
          "eventTime": [
            0.333333
          ],
          "events": [
            "OnAttack"
          ]
        }
      }
    }
  },
  "hash": "c02f39"
}